{
  "id": "45d3953d-3dbc-4cb5-b90b-47509d264b28",
  "revision": 0,
  "last_node_id": 18,
  "last_link_id": 8,
  "nodes": [
    {
      "id": 12,
      "type": "Fast Groups Bypasser (rgthree)",
      "pos": [
        759.563898682212,
        -2190.5081402683536
      ],
      "size": [
        357.05096435546875,
        183.21641540527344
      ],
      "flags": {},
      "order": 0,
      "mode": 0,
      "inputs": [],
      "outputs": [
        {
          "label": "可选连接",
          "name": "OPT_CONNECTION",
          "type": "*",
          "links": null
        }
      ],
      "title": "1.choice",
      "properties": {
        "matchColors": "",
        "matchTitle": "",
        "showNav": true,
        "showAllGraphs": true,
        "sort": "position",
        "customSortAlphabet": "",
        "toggleRestriction": "default",
        "widget_ue_connectable": {},
        "sdppp_widgetable_title": "1.选择"
      }
    },
    {
      "id": 1,
      "type": "CCXManager",
      "pos": [
        1227.851979687043,
        -1552.0293160054653
      ],
      "size": [
        318.5259765625,
        188.334875480135
      ],
      "flags": {},
      "order": 7,
      "mode": 0,
      "inputs": [
        {
          "name": "target_path",
          "type": "STRING",
          "widget": {
            "name": "target_path"
          },
          "link": 4
        }
      ],
      "outputs": [
        {
          "name": "运行状态",
          "type": "STRING",
          "links": [
            6
          ]
        }
      ],
      "properties": {
        "aux_id": "WWWEN8/ComfyUI-CCXManager",
        "ver": "8cc997cef80defe25c05fab936d6462b0c181f54",
        "Node name for S&R": "CCXManager",
        "widget_ue_connectable": {}
      },
      "widgets_values": [
        "url",
        "https://gitee.com/zombieyang/sd-ppp/raw/main/static/sd-ppp2_PS.ccx",
        "",
        "https://github.com/zombieyang/sd-ppp.git",
        "enable"
      ]
    },
    {
      "id": 2,
      "type": "CCXManagerCopy",
      "pos": [
        1224.706163764849,
        -1795.7940915934907
      ],
      "size": [
        340.64192417740685,
        161.72837367175202
      ],
      "flags": {},
      "order": 6,
      "mode": 0,
      "inputs": [
        {
          "name": "target_path",
          "type": "STRING",
          "widget": {
            "name": "target_path"
          },
          "link": 1
        }
      ],
      "outputs": [
        {
          "name": "运行状态",
          "type": "STRING",
          "links": [
            5
          ]
        }
      ],
      "properties": {
        "aux_id": "WWWEN8/ComfyUI-CCXManager",
        "ver": "8cc997cef80defe25c05fab936d6462b0c181f54",
        "Node name for S&R": "CCXManagerCopy",
        "widget_ue_connectable": {}
      },
      "widgets_values": [
        "url",
        "https://gitee.com/zombieyang/sd-ppp/raw/main/static/sd-ppp_PS.ccx",
        "",
        "https://github.com/zombieyang/sd-ppp.git",
        "enable"
      ]
    },
    {
      "id": 8,
      "type": "ShowText|pysssss",
      "pos": [
        1581.4602241720788,
        -1552.4964312454301
      ],
      "size": [
        210,
        106.58309936523438
      ],
      "flags": {},
      "order": 10,
      "mode": 0,
      "inputs": [
        {
          "name": "text",
          "type": "STRING",
          "link": 6
        }
      ],
      "outputs": [
        {
          "label": "字符串",
          "name": "STRING",
          "shape": 6,
          "type": "STRING",
          "links": null
        }
      ],
      "title": "#2.0Installation status",
      "properties": {
        "cnr_id": "comfyui-custom-scripts",
        "ver": "1.2.5",
        "Node name for S&R": "ShowText|pysssss",
        "widget_ue_connectable": {},
        "sdppp_widgetable_title": "#2.0Installation status"
      },
      "widgets_values": []
    },
    {
      "id": 7,
      "type": "ShowText|pysssss",
      "pos": [
        1591.550721131513,
        -1793.5660259874826
      ],
      "size": [
        210,
        127.05286407470703
      ],
      "flags": {
        "collapsed": false
      },
      "order": 9,
      "mode": 0,
      "inputs": [
        {
          "name": "text",
          "type": "STRING",
          "link": 5
        }
      ],
      "outputs": [
        {
          "label": "字符串",
          "name": "STRING",
          "shape": 6,
          "type": "STRING",
          "links": null
        }
      ],
      "title": "#1.0Installation status",
      "properties": {
        "cnr_id": "comfyui-custom-scripts",
        "ver": "1.2.5",
        "Node name for S&R": "ShowText|pysssss",
        "widget_ue_connectable": {},
        "sdppp_widgetable_title": "#1.0Installation status"
      },
      "widgets_values": []
    },
    {
      "id": 3,
      "type": "PrimitiveNode",
      "pos": [
        754.4311087477931,
        -1787.2953933469578
      ],
      "size": [
        431.9424133300781,
        109.77384948730469
      ],
      "flags": {},
      "order": 1,
      "mode": 0,
      "inputs": [],
      "outputs": [
        {
          "name": "STRING",
          "type": "STRING",
          "widget": {
            "name": "target_path"
          },
          "links": [
            1
          ]
        }
      ],
      "title": "2.sd-ppp_PS file path",
      "properties": {
        "Run widget replace on values": false,
        "widget_ue_connectable": {},
        "sdppp_widgetable_title": "2.sd-ppp_PS file path"
      },
      "widgets_values": [
        ""
      ],
      "color": "#332922",
      "bgcolor": "#593930"
    },
    {
      "id": 6,
      "type": "PrimitiveNode",
      "pos": [
        753.5699985178952,
        -1628.301842584666
      ],
      "size": [
        430.3104553222656,
        66.52769470214844
      ],
      "flags": {},
      "order": 2,
      "mode": 0,
      "inputs": [],
      "outputs": [
        {
          "name": "STRING",
          "type": "STRING",
          "widget": {
            "name": "target_path"
          },
          "links": [
            4
          ]
        }
      ],
      "title": "1.sd-ppp2_PS file path",
      "properties": {
        "Run widget replace on values": false,
        "sdppp_widgetable_title": "1.sd-ppp2_PS file path",
        "widget_ue_connectable": {}
      },
      "widgets_values": [
        ""
      ],
      "color": "#332922",
      "bgcolor": "#593930"
    },
    {
      "id": 16,
      "type": "Text Multiline",
      "pos": [
        767.3243443902849,
        -1495.3465184318563
      ],
      "size": [
        411.5644082214137,
        138.88270521589857
      ],
      "flags": {},
      "order": 3,
      "mode": 0,
      "inputs": [],
      "outputs": [
        {
          "label": "字符串",
          "name": "STRING",
          "type": "STRING",
          "links": null
        }
      ],
      "title": ".Instructions",
      "properties": {
        "cnr_id": "was-node-suite-comfyui",
        "ver": "ea935d1044ae5a26efa54ebeb18fe9020af49a45",
        "Node name for S&R": "Text Multiline",
        "widget_ue_connectable": {},
        "sdppp_widgetable_title": ".Instructions"
      },
      "widgets_values": [
        "↑Only modify the sd-PPP1.0 installation path and the sd-PPP2.0 installation path, do not modify other parameters.\n"
      ],
      "color": "#332922",
      "bgcolor": "#593930"
    },
    {
      "id": 15,
      "type": "PrimitiveNode",
      "pos": [
        1306.9385848956852,
        -2201.237425499773
      ],
      "size": [
        335.44370017524113,
        58.94870864858058
      ],
      "flags": {},
      "order": 4,
      "mode": 0,
      "inputs": [],
      "outputs": [
        {
          "name": "BOOLEAN",
          "type": "BOOLEAN",
          "widget": {
            "name": "auto_update"
          },
          "links": [
            8
          ]
        }
      ],
      "title": "1-1.ComfyUI side automatic update switch",
      "properties": {
        "Run widget replace on values": false,
        "widget_ue_connectable": {},
        "sdppp_widgetable_title": "1-1.ComfyUI side automatic update switch"
      },
      "widgets_values": [
        true
      ]
    },
    {
      "id": 14,
      "type": "ShowText|pysssss",
      "pos": [
        1881.0380708796906,
        -2171.1728071948296
      ],
      "size": [
        281.140234375,
        189.08892575839218
      ],
      "flags": {},
      "order": 11,
      "mode": 0,
      "inputs": [
        {
          "name": "text",
          "type": "STRING",
          "link": 7
        }
      ],
      "outputs": [
        {
          "label": "字符串",
          "name": "STRING",
          "shape": 6,
          "type": "STRING",
          "links": null
        }
      ],
      "title": "#Comfyui side automatic update status",
      "properties": {
        "cnr_id": "comfyui-custom-scripts",
        "ver": "1.2.5",
        "Node name for S&R": "ShowText|pysssss",
        "widget_ue_connectable": {},
        "sdppp_widgetable_title": "#Comfyui side automatic update status"
      },
      "widgets_values": []
    },
    {
      "id": 13,
      "type": "CCXRepoUpdaterNode",
      "pos": [
        1309.9499445325114,
        -2096.1140176587833
      ],
      "size": [
        500.15118211286654,
        141.66347767943307
      ],
      "flags": {},
      "order": 8,
      "mode": 0,
      "inputs": [
        {
          "name": "auto_update",
          "type": "BOOLEAN",
          "widget": {
            "name": "auto_update"
          },
          "link": 8
        }
      ],
      "outputs": [
        {
          "name": "STRING",
          "type": "STRING",
          "links": [
            7
          ]
        }
      ],
      "properties": {
        "aux_id": "WWWEN8/ComfyUI-CCXManager",
        "ver": "a33fc3ae580944a500443b1d0dba963d1b0e49c9",
        "Node name for S&R": "CCXRepoUpdaterNode",
        "widget_ue_connectable": {}
      },
      "widgets_values": [
        "https://github.com/zombieyang/sd-ppp.git",
        true,
        true
      ]
    },
    {
      "id": 10,
      "type": "Text Multiline",
      "pos": [
        1875.9791021458152,
        -1828.695244845373
      ],
      "size": [
        368.95543378613684,
        613.9595243246131
      ],
      "flags": {},
      "order": 5,
      "mode": 4,
      "inputs": [],
      "outputs": [
        {
          "label": "字符串",
          "name": "STRING",
          "type": "STRING",
          "links": null
        }
      ],
      "title": "#3.nstructions",
      "properties": {
        "cnr_id": "was-node-suite-comfyui",
        "ver": "ea935d1044ae5a26efa54ebeb18fe9020af49a45",
        "Node name for S&R": "Text Multiline",
        "widget_ue_connectable": {},
        "sdppp_widgetable_title": "#3.nstructions"
      },
      "widgets_values": [
        "#Node Description:\nSet to run once. Later, if there are updates on the SD-PPP (Photoshop side and ComfyUI side), it will automatically help you synchronize and update, completely eliminating the need to manually update plugins and nodes.\n\n#How to Use\n1. On the Photoshop side, find the Plug-ins directory in the installation folder, create two new folders inside the Plug-ins folder, and name them: sd-ppp_PS and sd-ppp2_PS respectively. (Please delete any folders from previously installed SD-PPP plugins) Prepare to copy the paths for sd-ppp_PS and sd-ppp2_PS\n\n2. The installation path for sd-PPP 1.0 should correspond to \"the file path of sd-ppp_PS\"\n\nThe installation path for sd-PPP 2.0 should correspond to \"the file path of sd-ppp2_PS\"\n\n3. If you have previously installed SD-PPP 2.0 on the Photoshop side, you can first save the workflow on the ComfyUI side, then open this workflow on the Photoshop side,https://github.com/WWWEN8/ComfyUI-CCXManager/blob/014d93a7657ab3daeabf64106d77fad683d09842/workflows/EN-1.png\n\n4. On the Photoshop side, check the boxes for \"ComfyUI side auto-update SDPPP\" and \"value\", then restart ComfyUI to automatically detect node updates. It will update automatically when there are updates (ignored when running on the ComfyUI side)\n\n5. Click to run\n\n6. Check the console for successful running information.\n\nFor more details, please read: https://github.com/WWWEN8/ComfyUI-CCXManager"
      ]
    }
  ],
  "links": [
    [
      1,
      3,
      0,
      2,
      0,
      "STRING"
    ],
    [
      4,
      6,
      0,
      1,
      0,
      "STRING"
    ],
    [
      5,
      2,
      0,
      7,
      0,
      "STRING"
    ],
    [
      6,
      1,
      0,
      8,
      0,
      "STRING"
    ],
    [
      7,
      13,
      0,
      14,
      0,
      "STRING"
    ],
    [
      8,
      15,
      0,
      13,
      0,
      "BOOLEAN"
    ]
  ],
  "groups": [
    {
      "id": 1,
      "title": "Photoshop automatically updates SDPPP on the side, and only this needs to be modified",
      "bounding": [
        733.9181110157513,
        -1908.828233992428,
        1101.8019001884932,
        718.5343801371691
      ],
      "color": "#3f789e",
      "font_size": 24,
      "flags": {}
    },
    {
      "id": 2,
      "title": "ComfyUI side automatic update switch",
      "bounding": [
        1256.1207473156398,
        -2279.1381976472517,
        994.4168342963733,
        348.3177200240864
      ],
      "color": "#3f789e",
      "font_size": 24,
      "flags": {}
    },
    {
      "id": 4,
      "title": "English Instructions",
      "bounding": [
        1865.9791021458152,
        -1902.295244845373,
        390.29725210906304,
        712.2231408277953
      ],
      "color": "#3f789e",
      "font_size": 24,
      "flags": {}
    }
  ],
  "config": {},
  "extra": {
    "ue_links": [],
    "ds": {
      "scale": 0.6588450000000025,
      "offset": [
        -516.7461851990311,
        2223.851118284794
      ]
    },
    "links_added_by_ue": [],
    "frontendVersion": "1.28.7"
  },
  "version": 0.4
}